pycirc
