Metadata-Version: 2.1
Name: pycirc
Version: 1.31
Summary: Python logic circuit modeling and simulation
Home-page: https://www.samyzaf.com/pycirc/pycirc.html
Author: Samy Zafrany
Author-email: samyz@technion.ac.il
License: MIT
Keywords: digital circuit logic modeling simulation
Platform: UNKNOWN
